lambda_repl/__init__.py
lambda_repl/__main__.py
lambda_repl/aliases.py
lambda_repl/grammar.lark
lambda_repl/main.py
lambda_repl/parsing.py
lambda_repl/py.typed
lambda_repl-1.2.0.dist-info/LICENSE
lambda_repl-1.2.0.dist-info/METADATA
lambda_repl-1.2.0.dist-info/WHEEL
lambda_repl-1.2.0.dist-info/entry_points.txt
lambda_repl-1.2.0.dist-info/top_level.txt
lambda_repl-1.2.0.dist-info/RECORD
