Metadata-Version: 2.1
Name: lambda-repl
Version: 1.2.0
Summary: REPL for the lambda calculus
Author-email: Eric Niklas Wolf <eric_niklas.wolf@mailbox.tu-dresden.de>
Project-URL: Repository, https://github.com/Deric-W/lambda_repl
Project-URL: Bugtracker, https://github.com/Deric-W/lambda_repl/issues
Classifier: Intended Audience :: Education
Classifier: License :: OSI Approved :: GNU General Public License v3 (GPLv3)
Classifier: Operating System :: OS Independent
Classifier: Programming Language :: Python :: 3 :: Only
Classifier: Topic :: Education
Classifier: Topic :: Utilities
Classifier: Typing :: Typed
Requires-Python: >=3.10
License-File: LICENSE
Requires-Dist: lambda-calculus (~=2.0)
Requires-Dist: lark (~=1.0)
